factcheck.py
setup.py
factcheck.egg-info/PKG-INFO
factcheck.egg-info/SOURCES.txt
factcheck.egg-info/dependency_links.txt
factcheck.egg-info/top_level.txt
test/test_factcheck.py
test/test_factcheck_python3.py