Metadata-Version: 1.1
Name: factcheck
Version: 1.3.0.2
Summary: A simple, extensible implementation of QuickCheck for Python
Home-page: http://github.com/npryce/python-factcheck
Author: Nat Pryce
Author-email: about-factcheck@natpryce.com
License: Apache 2.0
Platform: UNKNOWN
Classifier: Development Status :: 5 - Production/Stable
Classifier: Intended Audience :: Developers
Classifier: License :: OSI Approved :: Apache Software License
Classifier: Programming Language :: Python
Classifier: Programming Language :: Python :: 2
Classifier: Programming Language :: Python :: 2.7
Classifier: Programming Language :: Python :: 3
Classifier: Programming Language :: Python :: 3.2
Classifier: Natural Language :: English
Classifier: Topic :: Software Development :: Testing
Provides: factcheck
